[{"input":"step on no pets","date":"2016-02-29T22:42:56.439Z","pallyndromeCheckedCount":1},{"input":"taco cat","date":"2016-02-29T22:46:19.252Z","pallyndromeCheckedCount":1},{"input":"A man, a plan, a canal, Panama!","date":"2016-02-29T22:46:30.812Z","pallyndromeCheckedCount":1},{"input":"Amor, Roma","date":"2016-02-29T22:46:46.897Z","pallyndromeCheckedCount":1},{"input":"Was it a car or a cat I saw?","date":"2016-02-29T22:46:58.049Z","pallyndromeCheckedCount":1},{"input":"No 'x' in Nixon","date":"2016-02-29T22:47:11.894Z","pallyndromeCheckedCount":1},{"input":"Sator Arepo Tenet Opera Rotas","date":"2016-02-29T22:47:36.065Z","pallyndromeCheckedCount":1},{"input":"A Santa lived as a devil at NASA","date":"2016-02-29T22:47:59.836Z","pallyndromeCheckedCount":1},{"input":"A nut for a jar of tuna","date":"2016-02-29T22:48:14.012Z","pallyndromeCheckedCount":1},{"input":"Do geese see God?","date":"2016-02-29T22:48:37.516Z","pallyndromeCheckedCount":1},{"input":"A Toyota's a Toyota","date":"2016-02-29T22:48:48.689Z","pallyndromeCheckedCount":1}]